{
    "DESCRIPTION": "Muestra información sobre una carta",
    "SLASH_DESC": "Ingresa el código de una carta que quieras ver",
    "NO_CARD_FOUND": "No se ha podido encontrar tu última carta. Inténtalo proporcionando un código de carta",
    "INVALID_CARD_CODE": "{{author}} El código de carta que has proporcionado es inválido",
    "CARD_MORPHED": "Esa carta está morphed",
    "CARD_GLOWED": "Esa carta tiene aplicado el siguiente `Glow`: __{{glowName}} [`#{{viewCode}}`] {{isSuper}}__\n",
    "CARD_FONT": "Color de fuente: {{fontName}} [`#{{viewCode}}`]\n",
    "CARD_FRAMED": "Esa carta tiene el siguiente `Frame` aplicado __{{frameName}}__\n",
    "CARD_CFRAMED": "Esa carta tiene el siguiente `Frame` aplicado __{{frameName}}__ `{{frameCode}}`\n",
    "SHOW_GEN": "Mostrar Gen",
    "SERIES": "Serie",
    "NAME": "Nombre",
    "OWNED": "Propietario",
    "DROPPED": "Arrojado por",
    "CLAIM_BY": "Claimed por",
    "CLAIM ON": "Claimed en",
    "LEVEL": "Nivel",
    "HEALTH": "Salud",
    "POPULARITY": "Popularidad",
    "FOUGHT_OFF": "Enfrentado",
    "QUICKNESS": "Rapidez",
    "MORPHED_TIMES": "La carta ha recibido un morph `{{rolls}}` veces"
}
