{
    "DESCRIPTION": "Compra \"Wists\" del mercado a cambio de \"Gems\"",
    "CORRECT_USAGE": "{{author}} Uso correcto:` {{prefix}}mbuy <IDDeOferta> <CantidadDeWists>`",
    "INVALID_DEAL_ID": "{{author}} El ID de Oferta proporcionado es inválido",
    "CANNOT_PURCHASE": "{{user}} No puedes comprar esa oferta",
    "CANNOT_SELF": "{{user}} No puedes interactuar con tu propia oferta",
    "WIST_NOT_EXCEED": "{{author}} Esta oferta solo tiene {{amount}}`Wists`restantes para comprar",
    "PRODUCT": "Tú recibes:",
    "VALUE": "Tú pagas:",
    "RATE": "Tasa:",
    "CONFIRM_ASK": "¿Está seguro de que quieres confirmar esta transacción?",
    "ALREADY_IN_PURCHASE": "{{author}} Cancela o finaliza tu transacción previa para poder comenzar con una nueva!",
    "CANCELLED": "Estás intentando listar más `Wists` de los que tienes! ",
    "PURCHASE_FAILED": "Falló la compra de la oferta `{{dealId}}`",
    "PURCHASE_CANCELLED": "Esta oferta ya no esta disponible",
    "MISSING_GEMS": "Te faltan {{gemPrice}} `Gems`",
    "SOMETHING_WRONG": "Algo salió mal. Inténtalo de nuevo",
    "PURCHASE_SUCCESSFUL": "La transacción se realizó con éxito",
    "SUCCESS": "Se compraron {{wistAmount}} `Wists` por **{{gemPrice}}** `Gems`! | ID de oferta: {{dealId}}",
    "EMBED_TITLE": "MERCADO DE SOFI:"
}
