{
    "UNDOMORPH_DESCRIPTION": "カードから形態素を削除する",
    "UM_CATEGORY": "コスメティック",
    "UM_INVALID_USAGE": "有効なカードコードを提供してください",
    "INVALID_CODE": "{{author}} 入力されたカードコードが無効または自分のコレクションにありません",
    "NO_CHARACTER": "{{author}} このカードのキャラはSOFIに無効されたので利用不可能です",
    "NO_GIF": "{{author}} `GIF`カードにコスメティックを削除できません",
    "NOT_MORPHED": "{{author}} カードは変形していません",
    "EMBED_TITLE": "SOFI: UNDOMORPH",
    "UM_CONFIRMATION": "あなたはカードから形態素を削除しようとしています\nあなたのカードは以下のように見えます\nこのプロセスには100シルバーがかかります。",
    "NO_OWNER": "カードはもうあなたのものではありません",
    "SOMETHING_WENT_WRONG": "何か大変なことが起こりました.. <:sofi_cry:1008533719092559914>",
    "NOT_ENOUGH_SILVERS": "{{author}} この過程を実行する`{{currency}}`が足りません",
    "UM_SUCCESSFUL": "変形が正常に削除されました"
}
