{
    "DESCRIPTION": "- U kunt een bepaald personage opzoeken met behulp van het 'scl' commando. In het charlookup-menu kunt u de statistieken van de kaart controleren, hun 3D/geanimeerde afbeeldingen, gen-headboards, fan-scoreborden en de kaart-ID. De kaart-ID is nodig bij het indienen van afbeeldingen voor versies.",
    "CHAR_NOT_FOUND": "Kan personage niet vinden",
    "CHAR_NF_SENSITIVE": "Geen personage gevonden, [De lookup functie is hoofdlettergevoelig]",
    "EMBED_TITLE": "__Karakters opzoeken__",
    "NORMAL_LABEL": "Normale versie",
    "FAN_PTS_LABEL": "Voeg fanpunten toe",
    "NORMAL_DESC": "Toont de originele versie van de kaart",
    "ADD_FAN_PTS": "Verhoog je fanpunten voor de kaart",
    "3D_LABEL": "3D-versie",
    "3D_DESC": "Toont de 3D-versie van de kaart",
    "GIF_LABEL": "GIF-versie",
    "GIF_DESC": "Toont de GIF-versie van de kaart",
    "SERIES": "Serie",
    "NAME": "Naam",
    "CATEGORY": "Categorie",
    "WISHLISTED": "Op verlanglijstje",
    "GENERATED": "Gegenereerd",
    "BURNED": "Vernietigd",
    "VERSIONS": "Versies",
    "TOP_FANS": "Top Fans",
    "NO_FANS_FOUND": "Geen fans gevonden",
    "CARD_ID": "Kaart-ID",
    "ENTER_AMOUNT": "Voer het bedrag in",
    "MODAL_TITLE": "Voer het bedrag en de valutaname in",
    "CORRECT_EXAMPLE": "Juiste voorbeelden: `10 wists`,`3 gems`,`5000 silvers`",
    "MISSING_ITEMS": "Je mist: `{{amount} {{itemName}}`",
    "FAN_PTS_ADDED": "`+{{points}}` fanpunten toegevoegd voor: `{{amount}} {{itemName}}`",
    "3D_MAKER": "3D Maker",
    "CARD_MAKER": "Kaartmaker",
    "ANIMATED": "Geanimeerde versie",
    "GEN_CLAIMED": "Gens geclaimd: {{count}}/100",
    "TOP_OWNER": "Top eigenaren",
    "TOP_3D_OWNER": "Top 3D-eigenaren",
    "TOP_GIF_OWNER": "Top GIF-eigenaren",
    "NO_OWNER_FOUND": "Geen eigenaren gevonden...",
    "NO_3D_OWNER_FOUND": "Geen 3D-eigenaren gevonden...",
    "NO_GIF_OWNER_FOUND": "Geen GIF-eigenaren gevonden..."
}
