{
    "CARDINFO_DESCRIPTION": "Usar este comando com um código de carta específico exibirá informações mais específicas sobre a carta",
    "SLASH_DESC": "Insira o código de uma carta que você quer examinar",
    "NO_CARD_FOUND": "Não foi possível encontrar a sua última carta. Tente fornecer um código de carta",
    "INVALID_CARD_CODE": "{{author}} O código da carta fornecido é inválido ou não está na sua coleção",
    "CARD_GLOWED": "**{{isSuper}}Glow** aplicado: **{{glowName}} ** (`#{{viewCode}}`)\n",
    "CARD_FONT": "**Cores de Fonte:** \n- **Gen -** `{{genColorName}}` | `{{genColorCode}}` \n- **Nome -** `{{nameColorName}}` | `{{nameColorCode}}` \n- **Série -** `{{seriesColorName}}` | `{{seriesColorCode}}`",
    "CARD_FRAMED": "**Frame** aplicada: **{{frameName}}**\n",
    "CARD_CFRAMED": "**Frame** aplicada: **{{frameName}}** (`{{frameCode}}`)\n",
    "SHOW_GEN": "Mostrar Gen",
    "SERIES": "Série:",
    "NAME": "Nome:",
    "OWNED": "Propriedade de:",
    "DROPPED": "Dropado por:",
    "CLAIM_BY": "Pego por:",
    "CLAIM_ON": "Agarrado em:",
    "LEVEL": "Nível",
    "POPULARITY": "Popularidade",
    "FOUGHT_OFF": "Venceu",
    "QUICKNESS": "Pega em",
    "SUPER": "Super ",
    "SOME_GLOW": "Indisponível",
    "SOME_CODE": "Indisponível",
    "SOME_FRAME": "Indisponível",
    "EMBED_AUTHOR": "SOFI: CARDINFO (Level - {{level}})",
    "CLAIM_AT": "\nDropado em:",
    "MORPHED": "Morfada",
    "CARD_LAYERED": "**Layer** aplicada: **{{layerName}}**(`{{layerCode}}`)\n"
}
