{
    "PULL_DESCRIPTION": "Sa pamamagitan ng command na ito, maaari mong i-convert ang Wists at Gems sa iba't ibang mga items, kabilang ang Fragments na ginagamit upang lumikha ng GIF cards",
    "PULL_AMT": "{{author}} Tamang paggamit: `{{prefix}}pull <1/10>`",
    "INFO_1": "Kailangan mo ng 8 na **Fragments** upang lumikha ng isang **GIF** na bersyon ng isang karakter",
    "INFO_2": "Mayroong maximum na **100** **GIF** variants bawat karakter",
    "INFO_3": "Ipagtapon ang mga `Fragments` upang makakuha ng mga `Charms`",
    "PULLS": "SOFI: PULLS",
    "PULL_COUNT": "Bilang ng pagPull: [ {{count}} ]",
    "MISSING_CURR": "{{user}} Kulang ang iyong `{{currName}}` para sa prosesong ito",
    "AMOUNT": "Natanggap mo: {{currencyEmoji}} **{{amount}}x** {{pullOutcome}}",
    "PULL_COUNT_WIST": "Bilang ng Pull:[ {{pullcount}}]",
    "RATES": "Porsiyento",
    "PULL_CHANCES": "**__Mga Posibilidad__**"
}
