{
    "DESCRIPTION": "Bumili ng \"Items\" mula sa \"Shop\" ng Sofi",
    "GUILD": "Samahan",
    "GEMS": "Bumili",
    "SOFI_SHOP": "SOFI: SHOP ({{section}})",
    "DROP": "> Maaaring gamitin ang `Drops` para **mag-drop** ng higit pang mga card habang nasa cooldown ka pa",
    "GRAB": "> Maaaring gamitin ang `Grabs` para **grab** ng higit pang mga card habang nasa cooldown ka pa",
    "CUBE": "> Ginagamit ang `Cube` upang gawing mga variant ng `3D` ang iyong mga card",
    "TP": "> Ang `Trade Pass` ay kinakailangan upang masagawa ang trade sa ibang mga players",
    "GUILD_STONE": "> Ang `Guild Stones` ay kinakailangan upang lumikha ng isang `Guild`",
    "BG": "> Maaaring ilapat ang `Mga Background` sa mga `3D` card",
    "RECHARGE": "> Ang `Recharges` ay maaaring gamitin upang magamit mo ang iyong `Glow`",
    "GEN_S": "> Ang mga `Scratchers` ay nagpapakita ng `Gen` ng isang `Event` card",
    "STAT_RESET": "> Nire-reset ang inilalaang pag-upgrade ng stat ng isang card",
    "BUY_DROP": "`1)` `{{prefix}}buy drops`: <:wist:870339503427027005> 1 Wist ➜ <:sofidrop:915966705811988570> 1 Drop",
    "BUY_GRAB": "`2)` `{{prefix}}buy grabs`: <:wist:870339503427027005> 1 Wist ➜ <:sofigrab:915967559369637988> 1 Grab",
    "BUY_CUBE": "`3)` `{{prefix}}buy cubes`: 1 x Each Crystal ➜ <a:soficube:915625529313460265> 1 Cube",
    "BUY_TP": "`4)` `{{prefix}}bumili ng tp`: Bump 1 o 20 beses sa site",
    "BUY_GUILD_STONE": "`5)` `{{prefix}}buy guildstone`: <:_:915619222229512213> 25,000 Silvers ➜ <:_:869577168282325042> 1 Guild Stone",
    "DONATE_SUPPORT": "Suportahan kami sa pamamagitan ng pagiging patron!",
    "UTILITY": "Kagamitan",
    "BUY_STAT_RESET": "**1) `{{prefix}}buy sr` | <:elixir:979673719884636210> 2,000x `Elixir` ➜ 🌀 1x `Stat Reset`**"
}
