{
  "BID_DESCRIPTION": "Enchère dans les enchères",
  "BID_CATEGORY": "Cartes",
  "WRONG_USAGE": "{{author}} utilisation correcte : `sbid <auctionID> <montant>`",
  "INVALID_ID": "{{author}} ID d'enchère invalide fourni. Veuillez vérifier à nouveau",
  "INVALID_AMOUNT": "{{author}} le montant doit être un nombre",
  "NO_AMOUNT": "{{author}} vous n'avez pas {{amount}} {{currency}}",
  "EMBED_TITLE": "SOFI : ENCHÈRE",
  "CONFIRM_BID": "{{author}} êtes-vous sûr de vouloir placer une enchère de {{amount}} {{currency}} sur l'enchère `{{auctionId}}`",
  "BID_NOTE": "Lorsque vous placez une nouvelle enchère, le montant de l'enchère précédente sera ajouté à l'inventaire et le nouveau montant de l'enchère sera déduit",
  "EMBED_FOOTER": "Note : Les enchères sont anonymes",
  "MINIMUM_BID": "Annulation : L'enchère minimale doit être de `{{amount}}`{{currency}} et vous devez avoir ce montant",
  "ALREADY_MAX_BIDDER": "Vous êtes déjà le plus offrant",
  "OUTBIDDED": "Vous êtes surenchéri dans l'enchère ID `{{auctionId}}`",
  "SUCCESSFUL_BID": "L'enchère a été placée avec succès",
  "EMBED_BID_TITLE": "SOFI : ENCHÈRE [{{auctionId}}]",
  "EMBED_BID_DESCRIPTION": "> Bienvenue dans l'enchère SOFI :\n> Utilisez `sbid <auctionID> <montant>` pour placer une enchère sur la carte\n> Note : Les enchères seront anonymes",
  "CARD_DETAILS": "Détails de la carte",
  "BID_GEN": "> Gén : `{{gen}}`",
  "BID_NAME": "> Nom : {{name}}",
  "BID_SERIES": "> Série : {{series}}",
  "BID_ACCEPTED_IN": "Enchère acceptée dans : {{currencyEmoji}} {{currencyName}}",
  "TOTAL_BIDS": "> Meilleure enchère : {{bids}}",
  "BID_SOFI_PLAYER": "> Un joueur Sofi - {{amount}}",
  "MORE_BIDDERS": "{{bidders}} de plus..."
}
