{
    "NO_GIF_3D": "{{author}} Vous ne pouvez pas changer le texte sur les cartes **3D** ou **GIF**",
    "TOGGLE_GEN": "Basculer la Gen",
    "EMBED_TITLE": "SOFI: FONT",
    "TOGGLE_GEN_LABEL": "Basculer la Gen",
    "TOGGLE_ALL_LABEL": "Tout Basculer",
    "TOGGLE_NAME_LABEL": "Basculer le Nom",
    "TOGGLE_SERIES_LABEL": "Basculer la Série",
    "COLOR_NAME_LABEL": "Couleur du Nom",
    "GLOW_CODE_INVALID": "Le code du **Glow** que vous avez fourni est invalide ou n'est pas dans votre collection",
    "GLOW_MODAL_LABEL": "Entrez le Glow code",
    "COLOR_SERIES_LABEL": "Couleur de la Série",
    "PROCESS_COMPLETED": "Le processus a été complété avec succès",
    "GLOW_MODAL_PLACEHOLDER": "ex. #1vg0a1",
    "SAVE_MODAL_LABEL": "Êtes-vous sûr(e)?",
    "SAVE_MODAL_PLACEHOLDER": "Oui",
    "SAVE_LABEL": "Sauvegarder",
    "NOT_ENOUGH_SILVERS": "Vous n'avez pas assez de **Silvers** pour faire cet achat",
    "GLOW_MODAL_TITLE": "Code du Glow: {{type}}",
    "TOGGLE_SERIES": "Basculer la Série",
    "COLOR_GEN": "Couleur de Gen",
    "FONT_CATEGORY": "Cosmétiques",
    "ERROR_FINDING_CARD": "{{author}} Le code de la carte que vous avez fourni est invalide ou n'est pas dans votre collection",
    "BASE_FONT": "Police de Base",
    "COLOR_SERIES": "Couleur de Série",
    "SELECT_MENU_PLACEHOLDER": "Sélectionnez la Police",
    "COLOR_GEN_LABEL": "Couleur de la Gen",
    "NOT_ENOUGH_GEMS": "Vous n'avez pas assez de **Gems** pour faire cet achat",
    "FONT_DESCRIPTION": "Vous pouvez utiliser cette commande afin d'appliquer un Glow sur la police d'une carte ou pour basculer sa Gen, Nom ou Série.",
    "COLOR_NAME": "Couleur du Nom",
    "TOGGLE_NAME": "Basculer le Nom",
    "PRICE": "Prix"
}
