{
    "DESCRIPTION": "Ouvre des coffres et des lootboxes",
    "SLASH_DESC_1": "Entrez L'-\"Item\" que vous voulez ouvrir",
    "SLASH_DESC_2": "Entrez le montant.",
    "CORRECT_USAGE": "{{author}} Utilisation correcte: `{{prefix}}open <NomDItem> <Montant>`",
    "EMPTY_INV": "{{author}} Votre `Inventory` est vide",
    "CHARM_MISSING": "{{author}} Vous n'avez pas de `Charms`",
    "SOFI_CARDS_MISSING": "{{author}} Il n'y a actuellement pas assez de cartes dans la collection de Sofi",
    "CONGRATS": "Félicitations! Vous avez reçu:",
    "SERIES": "Série:",
    "NAME": "Nom:",
    "CHEST_INFO": "Les Coffres d'Event peuvent encore être ouverts après la fin d'un event",
    "PROVIDE_NUM": "Veuillez fournir un nombre entre **1 & 10**",
    "CHEST_MISSING": "Vous n'avez pas de **{{replacedArg}}** Coffre`{{chestName}}` dans votre `Inventory`",
    "COMMON_INFO_1": "Vous avez ouvert **{{totalChests}}** Coffres`{{chestName}}`",
    "ITEMS_FOUND": "Objets obtenus:\n",
    "COMMON_RARE_FOOTER": "Vous pouvez obtenir un coffre {{chestName}} pour chaque série de {{count}} `Daily` consécutif",
    "EXOTIC_DIVINE_FOOTER": "Vous pouvez obtenir un coffre {{chestName}} pour {{count}} `Votes` chaque mois",
    "ITEM_MISSING": "Vous n'avez pas {{itemName}} dans votre inventaire",
    "CORRECT_USAGE_2": "`Items` pouvant être ouvert: `Chests`, `Charms`"
}
