{
    "DESCRIPTION": "Koleksiyonunu\"sc\" komutu ile görüntüleyebilirsin.\n- Koleksiyonun Ad, Kozmetik, İstatistikler ve daha fazlasına göre sıralanabilir\n- \"İstek Listesi\", \"Gen\" veya \"Tag\" adına göre de filtrelenebilir\n- Koleksiyonundaki etiketlenmemiş kartları bulmak için \"sc t:ut\" komutunu kullan",
    "SLASH_CMD_DESC": "Kart koleksiyonunu görüntüler",
    "SLASH_DESC": "Koleksiyonunu görmek için bir kullanıcı belirtin",
    "SLASH_DESC2": "Koleksiyona uygulamak istediğin filtreleri gir",
    "PLAYER_NOT_EXIST": "{{author}} Bu kullanıcı mevcut değil",
    "PLAYER_PRIVATE": "{{author}} Bu kullanıcının koleksiyonu gizlidir!",
    "NO_RESULTS": "{{author}} Sonuç bulunamadı!",
    "NO_CARDS_FOUND": "{{author}} Aramanla eşleşen kart bulunamadı",
    "NOTHING_FOUND": "Hiçbir şey bulunamadı",
    "CHOOSE_SORTING": "Sıralama Seç",
    "SORT_CHAR": "İsme Göre Sırala",
    "SORT_SERIES": "Seriye Göre Sırala",
    "SORT_GEN": "Gen'e Göre Sırala",
    "SORT_WL": "İstek Listesine Göre Sırala",
    "CHECK_COSMETICS": "Kozmetikleri Kontrol Et",
    "3D_AVAIL": "3D Kullanılabilirliği",
    "SORT_ATK": "Saldırı Gücüne Göre Sırala",
    "SORT_DEF": "Defansa Göre Sırala",
    "SORT_SPEED": "Hıza Göre Sırala",
    "SORT_HP": "Cana Göre Sırala",
    "SORT_DUPE": "Yinelenen Kartlara Göre Sırala",
    "SHOWING PAGE": "Gösterilen sayfa: {{page}}/{{pages}}",
    "ALL_UNTAG_SUCCESS": "{{taglength}} kartın etiketi başarıyla kaldırıldı",
    "ALL_TAG_SUCCESS": "{{author}} {{taglength}} kart başarıyla etiketlendi",
    "PLEASE_WAIT": "Lütfen Bekle <a:ping:876612181725167687>",
    "NO_TAG_FOUND": "Henüz herhangi bir `Tag`ın yok. `stc <TagAdı> <Emoji>` komutunu kullanarak oluşturabilirsin"
}
