{
    "DESCRIPTION": "Membeli \"Item\" dari \"Shop\" Sofi",
    "SLASH_DESC": "Masukkan nama Item yang ingin anda beli",
    "SLASH_DESC2": "Masukkan jumlah item",
    "SLASH_DESC3": "Masukkan kode dari Background yang ingin kamu beli. [HANYA BERFUNGSI JIKA ITEM DIPILIH SEBAGAI BACKGROUND]",
    "NO_ITEM": "{{author}} Penggunaan yang benar: `{{prefix}}buy <ItemName> <Jumlah>`",
    "TRADEPASS_INFO": "Kunjungi situs web kami di bawah ini untuk **Bump** dan tukarkan poin anda dengan item yang berbeda, termasuk `Trade Pass`",
    "CORRECT_USAGE": "{{user}} Penggunaan yang benar: `{{prefix}}buy bg <Background-ID> <Jumlah>`",
    "INVALID_BG_AMOUNT": "{{author}} Anda tidak dapat membeli barang dengan jumlah negatif",
    "INVALID_BG_ID": "{{author}} Tidak dapat menemukan **Background** dengan ID tersebut",
    "INVALID_ITEM_PROVIDED": "{{user}} Item yang Anda berikan tidak valid"
}
