{
    "UNLOCKGLOW_DESCRIPTION": "Menghasilkan Glow secara acak. Anda dapat menggunakan Glow untuk menambahkan efek cahaya pada batas bingkai kartu Anda, mengubah warna teks pada kartu Anda, atau mengubah warna profil Anda.",
    "UG_CATEGORY": "Kosmetik",
    "EMBED_TITLE": "SOFI: GENERATE GLOW",
    "UNLOCK_GLOW_CONFIRM": "Apakah anda yakin ingin membeli **Glow** acak seharga **100** {{currency}}?",
    "CANCELLED_UNLOCK_GLOW": "Proses telah dibatalkan",
    "NOT_ENOUGH_GEMS": "{{author}} Anda tidak memiliki cukup **Gems**",
    "EMBED_GLOW_TITLE": "SOFI: GENERATE GLOW",
    "UNLOCK_GLOW_SUCCESS": "{{author}} Berhasil membeli **Glow**",
    "GLOW_INFO": "Nama: **{{glowName}}**\nKode: **`#{{glowCode}}`**\nKemurnian: **{{purity}}%**"
}
