{
    "VG_DESCRIPTION": "Tampilkan daftar \"Glow\" pengguna",
    "VG_CATEGORY": "Kosmetik",
    "VG_SLASH_DESC1": "Pilih pengguna yang \"Glow\" nya ingin Anda lihat",
    "VG_SLASH_DESC2": "Masukkan nama tag yang ingin anda filter",
    "VG_SLASH_DESC3": "Masukkan kode \"Glow\" yang anda ingin periksa",
    "NO_GLOWS": "{{author}} Tidak ada `Glow` yang ditemukan dari pengguna tersebut",
    "SUPER": "Super",
    "EMBED_TITLE": "SOFI: VIEW `GLOWS`",
    "EMBED_FOOTER": "Menampilkan halaman: {{page}}/{{totalPages}} | Total: {{count}}",
    "NO_GLOWS_FOUND": "{{author}} Anda tidak memiliki `Tag` dengan nama: `{{tagName}}`",
    "CANNOT_FIND_GLOW": "{{author}} Tidak dapat menemukan `Glow` dengan kode: `{{glowCode}}`",
    "EMBED_GLOW_TITLE": "SOFI: VIEW `GLOWS`",
    "NAME": "`Nama:     ` ➜ **{{name}}**",
    "CODE": "`Kode         ` ➜ `#{{code}}`",
    "STATUS": "`Status        ` ➜**{{status}}**",
    "TYPE": "`Tipe:     ` ➜ **{{type}}**",
    "OWNER": "`Pemilik      ` ➜ <@{{ownerId}}>",
    "PURITY": "Kemurnian      ➜ {{purity}}",
    "NO_GLOWS_SELF": "{{author}} Anda belum memiliki `Glows`",
    "INVALID_USER": "{{author}} Tidak dapat menemukan pengguna tersebut",
    "PURITY2": "Kemurnian2          ➜ {{purity2}}",
    "SORT_BUTTON_LABEL": "Urutkan"
}
