{
    "GLOW_NOT_FOUND": "{{author}} Mã **Glow** bạn cung cấp không hợp lệ hoặc không có trong kho đồ của bạn",
    "GLOWNAME_DESCRIPTION": "Đổi tên một Glow đã chọn",
    "GN_CATEGORY": "Đồ trang trí",
    "UNLOCK_GLOWS": "{{author}} Bạn không có **Glow** nào",
    "WRONG_GLOWCODE_FORMAT": "{{author}} Mã **Glow** phải bắt đầu bằng `#`",
    "GLOW_NAME_LONG": "{{author}} Tên **Glow** chỉ có thể dài tối đa 25 ký tự",
    "PROFANE_GLOW_NAME": "{{author}} Tên **Glow** của bạn không được chứa từ ngữ tục tĩu hoặc từ ngữ xúc phạm",
    "EMBED_TITLE": "SOFI: GLOW NAME",
    "MISSING_ITEMS": "{{author}} Bạn không có đủ **{{currency}}** cho quá trình này",
    "GLOWNAME_CHANGE_SUCCESSFUL": "{{author}} Đã đổi tên **Glow** của bạn sang `{{newName}}`",
    "WRONG_USAGE": "{{author}} Cách sử dụng đúng: `{{prefix}}gn <#GlowCode> <NewName>`",
    "GLOWNAME_CHANGE_CONFIRMATION": "Bạn có chắc muốn đổi tên **Glow** của bạn từ `{{oldName}}` sang `{{newName}}` không?",
    "GLOW_NAME_EXISTS": "{{author}} Tên đó đã được dùng cho một **Glow** khác"
}
