{
    "GUILDINFO_DESCRIPTION": "This command is used to access a guild's embed, containing member details, vault, crafting, boosts, and other guild features depending on if it's your guild as well as permissions.",
    "GUILDINFO_CATEGORY": "Guilds",
    "BUFF_DESC_1": "Increase the quest success rate",
    "BUFF_DESC_2": "Increase the amount of **Shards** and **Silver** earned from quests",
    "BUFF_DESC_3": "Reduce the costs of guild crafts",
    "BUFF_DESC_4": "Find additional loot from raids",
    "BUFF_DESC_5": "Increase the speed of guild crafts",
    "BUFF_DESC_6": "Reduce the cost of repairing equipment",
    "GI_REQUIRES": "Requires: {{info}}",
    "GI_LEVEL": "LVL {{level}}",
    "PLAYER_NOT_EXIST": "{{author}} Could not find that user",
    "NOT_IN_GUILD": "{{author}} You are not in any guild",
    "INVALID_ID": "{{author}} Invalid ID provided",
    "CANT_FIND_GUILD": "{{author}} The guild information could not be retrieved. Please provide a guild ID or mention a guild member.",
    "GI_FOUNDER": "Founder",
    "GI_RATING": "Rating",
    "GI_MEMBERS": "Members",
    "INFO_EMBED_FOOTER": "Guild ID: {{id}} | Created on",
    "GUILD_MENU_LABEL": "Guild Info",
    "GUILD_MENU_DESC": "Main information about the guild",
    "VAULT_MENU_LABEL": "Vault",
    "VAULT_MENU_DESC": "Vault info",
    "GUILD_MEMBER_MENU_LABEL": "Guild Members",
    "GUILD_MEMBER_MENU_DESC": "List of guild members",
    "GUILD_SERVER_MENU_LABEL": "Guild Server Invite",
    "GUILD_SERVER_MENU_DESC": "Unlock Guild Server Invite feature for {{amount}} Gems",
    "GUILD_IMAGE_MENU_LABEL": "Guild Image",
    "GUILD_IMAGE_MENU_DESC": "Unlock Guild Image feature for 100 Wists",
    "MEMBER_SLOT_MENU_LABEL": "Guild Member Slot",
    "MEMBER_SLOT_MENU_DESC": "+1 slot for {{amount}} Silver",
    "EDIT_GUILD_MENU_LABEL": "Edit Guild",
    "EDIT_GUILD_MENU_DESC": "Edit guild features",
    "GUILD_UPGRADE_MENU_LABEL": "Guild Upgrade",
    "GUILD_UPGRADE_MENU_DESC": "Upgrade the guild",
    "GUILD_INFO_MENU_PLACEHOLDER": "Select a Category",
    "GUILD_BOOST_MENU_PLACEHOLDER": "Select a Boost",
    "DONATE_BUTTON_LABEL": "Donate",
    "WITHDRAW_BUTTON_LABEL": "Withdraw",
    "DESCRIPTION_BUTTON_LABEL": "Description",
    "BANNER_BUTTON_LABEL": "Banner",
    "COLOR_BUTTON_LABEL": "Color",
    "CRAFT_PERM_BUTTON_LABEL": "Crafting Permissions",
    "GUILD_IMAGE_BUTTON_LABEL": "Guild Image",
    "CRAFTING_BUTTON_LABEL": "Crafting",
    "BACK_BUTTON_LABEL": "Back",
    "ITEM_BUTTON_LABEL": "Select Item",
    "QUANTITY_BUTTON_LABEL": "Select Quantity",
    "SLOT_BUTTON_LABEL": "Slot {{slot}}",
    "NAME_BUTTON_LABEL": "{{amount}} | Guild Name",
    "INVITE_BUTTON_LABEL": "Guild Server Invite",
    "STATS_BUTTON_LABEL": "Stats",
    "BOOST_BUTTON_LABEL": "Boost",
    "VAULT_LOGS_BUTTON_LABEL": "Vault Logs",
    "CRAFT_BUTTON_LABEL": "Craft",
    "CRAFTING_ITEM_MODAL_LABEL": "Enter the item number:",
    "CRAFTING_ITEM_MODAL_PLACEHOLDER": "Example: 1 | 2 | 3",
    "CRAFTING_ITEM_MODAL_TITLE": "Select Item",
    "INVALID_ITEM": "Invalid item ID provided",
    "GUILD_LEVEL_ACCESS": "Guild must be level 6 and have 10 members to access crafting **Guild Packages**",
    "CRAFTING_EMBED_TITLE": "SOFI: CRAFTING ({{itemName}})",
    "GI_GUILD_VAULT": "__**Guild Vault**__",
    "CRAFTING_AMOUNT_MODAL_LABEL": "Enter the amount to craft:",
    "CRAFTING_AMOUNT_MODAL_PLACEHOLDER": "Example: 1 | 2 | 3",
    "CRAFTING_AMOUNT_MODAL_TITLE": "Select Quantity",
    "INVALID_MAX_AMOUNT": "Invalid amount provided | Max quantity: `{{maxAmount}}`",
    "NAME_MODAL_LABEL": "Enter the new name for your guild:",
    "NAME_MODAL_PLACEHOLDER": "Example: MyNewGuildName",
    "NAME_MODAL_TITLE": "Change Guild Name",
    "FOUNDERS_GM_NAME": "Only **Founders** and **Guildmasters** can set the guild name",
    "NAME_NEED_GEMS": "You need **{{amount}}** **Gems** in vault to change the guild name",
    "NAME_CHANGE_SUCCESS": "Guild name has been successfully changed",
    "IMAGE_MODAL_LABEL": "Enter the image URL:",
    "IMAGE_MODAL_PLACEHOLDER": "e.g.: https://some.com/img.png | {{width}} x {{height}}",
    "IMAGE_MODAL_TITLE": "Edit Guild Image",
    "FOUNDERS_GM_IMAGE": "Only **Founders** and **Guildmasters** can set the guild image",
    "INAVLID_IMAGE_URL": "Invalid image URL provided",
    "IMAGE_WRONG_DIMENSION": "Image dimensions must be {{width}} x {{height}}",
    "IMAGE_CHANGE_SUCCESS": "Guild image has been successfully set",
    "INVITE_MODAL_LABEL": "Enter the server invite link:",
    "INVITE_MODAL_PLACEHOLDER": "Example: https://discord.gg/sofi",
    "INVITE_MODAL_TITLE": "Edit Server Invite",
    "FOUNDERS_GM_INVITE": "Only **Founders** and **Guildmasters** can set the guild invite",
    "INAVLID_INVITE_URL": "Invite should begin with `https://discord.gg/`",
    "INVITE_CHANGE_SUCCESS": "Guild server invite has been successfully set",
    "DONATE_MODAL_LABEL": "Enter the amount and item name to donate:",
    "DONATE_MODAL_PLACEHOLDER": "Example: 15 Cubes | Silver and Wists cannot be withdrawn",
    "DONATE_MODAL_TITLE": "Donate to Vault",
    "INVALID_ITEM_NAME": "Invalid item name provided",
    "CANNOT_DONATE_SWAPS": "You cannot donate Swaps to vault",
    "INVALID_AMOUNT": "Invalid amount provided",
    "NO_AMOUNT_INV": "You do not have that amount in your inventory",
    "VAULT_EMBED_TITLE": "{{name}} Vault",
    "DONATED_TO_VAULT": "> {{user}} donated **{{amount}}** **{{itemName}}** to the vault",
    "WITHDRAW_MODAL_LABEL": "Enter the amount and item name to withdraw:",
    "WITHDRAW_MODAL_PLACEHOLDER": "Example: 15 Cubes",
    "WITHDRAW_MODAL_TITLE": "Withdraw from Vault",
    "VAULT_NO_AMOUNT": "There is not enough amount in the vault",
    "NO_ITEM_VAULT": "There are no items in the vault",
    "WITHDRAW_FROM_VAULT": "> {{user}} has withdrawn **{{amount}}** **{{itemName}}** from the vault",
    "DESCRIPTION_MODAL_LABEL": "Enter the description:",
    "DESCRIPTION_MODAL_PLACEHOLDER": "Example: This is a nice guild",
    "DESCRIPTION_MODAL_TITLE": "Set Guild Description",
    "LONG_DESCRIPTION": "Guild description must be less than **250** characters and less than **5** lines",
    "NO_LINKS_IN_DESCRIPTION": "You cannot use any links in the guild description",
    "DESCRIPTION_CHANGE_SUCCESS": "Guild description has been successfully set",
    "BANNER_MODAL_LABEL": "Enter the banner URL:",
    "BANNER_MODAL_PLACEHOLDER": "Example: https://media.discord/someurl.png",
    "BANNER_MODAL_TITLE": "Set Guild Banner",
    "INVALID_BANNER": "Invalid URL provided",
    "BANNER_SET_SUCCESS": "Guild banner has been successfully set",
    "GLOW_MODAL_LABEL": "Enter the Glow code:",
    "GLOW_MODAL_PLACEHOLDER": "Example: #aadffe",
    "GLOW_MODAL_TITLE": "Set Embed Color",
    "INVALID_GLOW": "The **Glow** code you provided is either invalid or not in your inventory",
    "COLOR_SET_SUCCESS": "Embed color has been successfully updated",
    "PERMISSION_MODAL_LABEL": "Enter the permission level:",
    "PERMISSION_MODAL_PLACEHOLDER": "Adventurer: 0, Veteran: 1, GuildMaster: 2, Founder: 3",
    "PERMISSION_MODAL_TITLE": "Set Crafting Permission Level",
    "INVALID_PERMISSION": "Invalid permission level provided.\n\n**Available levels:**\nAdventurer: 0\nVeteran: 1\nGuildMaster: 2\nFounder: 3",
    "PERMISSION_EMBED_FOOTER": "Crafting Permission Level: {{level}}",
    "PERMISSION_SET_SUCCESS": "Crafting permission level has been successfully updated",
    "BOOST_MODAL_LABEL": "Enter the amount of Cubes:",
    "BOOST_MODAL_PLACEHOLDER": "Example: 15 Cubes",
    "BOOST_MODAL_TITLE": "SOFI: BOOST",
    "NOT_ENOUGH_CUBES": "> There is not enough amount in the vault",
    "BOOST_LEVEL_MAX": "> The boost level has already reached its maximum",
    "BOOST_EMEBD_TITLE": "SOFI: GUILD BOOST",
    "BOOST_EMBED_FOOTER": "You can change which stats are boosted from the menu",
    "CANNOT_HANDLE_MEMBERS": "Guilds of over 40 members cannot be handled",
    "SLOT_UNLOCKED": "Guild Member Slot unlocked 🔓: \n\n+1 Member Slot",
    "NOT_ENOUGH_SILVER": "There is not enough **Silver** in the vault to unlock a slot",
    "CANNOT_VIEW_VAULT": "You cannot view the vaults of other guilds",
    "SPREADSHEET_NOTE": "Use \"{{prefix}}sheet guild\" to get the spreadsheet of vault logs.\nWists and Silver cannot be withdrawn.",
    "UNLOCK_FEATURES_MENU_PLACEHOLDER": "Unlock Features",
    "UPGRADE_EMBED_TITLE": "SOFI: GUILD UPGRADE",
    "UPGRADE_EMBED_DESCRIPTION": "> **Guild Member Slots - {{memSlots}}** \n> Available guild slots: `{{availableSlots}}` \n> Slot unlock cost: `{{slotAmount}} {{slotCurrency}}` \n\n> **Guild Server Invite - {{inviteToggle}}** \n> Unlock cost: `{{inviteAmount}} {{inviteCurrency}}` \n\n> **Guild Image - {{imageToggle}}** \n> Unlock cost: `{{imageAmount}} {{imageCurrency}}`",
    "GI_UNLOCKED": "Unlocked  🔓",
    "GI_LOCKED": "Locked  🔒",
    "MEMBERS_EMBED_TITLE": "SOFI: GUILD MEMBERS - {{name}}",
    "IMAGE_EMBED_TITLE": "SOFI: UNLOCK GUILD IMAGE",
    "UNLOCK_IMAGE_CONFIRM": "Do you want to unlock guild image feature for **{{amount}}** **{{currency}}**?",
    "UNLOCK_PERM_ERROR": "Only **Founders** and **Guildmasters** can unlock this feature",
    "INVITE_EMBED_TITLE": "SOFI: UNLOCK GUILD SERVER INVITE",
    "UNLOCK_INVITE_CONFIRM": "Do you want to unlock guild invite feature for **{{amount}}** **{{currency}}**?",
    "NOT_ENOUGH_CRAFT_RESOURCES": "There are not enough resources in the vault to craft this item",
    "MAXIMUM_CRAFTING_LIMIT": "Maximum crafting limit of **Guild Packages** reached",
    "CRAFT_SLOT_OCCUPIED": "Slot {{slot}} is occupied",
    "CRAFTING_STARTED": "Started crafting **{{itemName}}**",
    "ITEM_EMBED_TITLE": "SOFI: CRAFTING",
    "ITEM_EMBED_DESCRIPTION": "The items collected in your vault can be used to craft various items. \nResources will be directly consumed from your vault. \nThe crafted item will be directly transferred to your inventory. \nPermission level can be set by **Founders** and **Guildmasters**. \n\nGlobal **Guild Packages** count: {{packageCount}}/300 \nPermission Level: **{{permLevel}}** \nCrafting time \nCrafting cost",
    "STATS_EMBED_TITLE": "SOFI: GUILD STATS",
    "GI_POINTS_SCORED": "Points Scored",
    "GI_RAIDS_WON": "Raids Won",
    "GI_BATTLES_WON": "Battles Won",
    "GI_ELIXIR_EARNED": "Elixir Earned",
    "GI_DAMAGE_GIVEN": "Damage Dealt",
    "GI_SEASON_STATS": "__**SEASON STATS**__",
    "SEASON_REWARD_NOTE": "Guilds get **Charms** at the end of every season based on the achieved rank",
    "VAULT_LOGS_EMPTY": "> Vault logs are empty",
    "GI_DONATED": "Donated",
    "GI_WITHDRAWN": "Withdrawn",
    "GI_BOOST": "Boost",
    "VAULT_LOGS_EMBED_TITLE": "GUILD: VAULT LOGS",
    "INVITE_UNLOCK_SUCCESS": "The guild server invite feature has been successfully unlocked",
    "NOT_ENOUGH_ITEM_VAULT": "Not enough **{{itemName}}** in the vault",
    "IMAGE_UNLOCK_SUCCESS": "The guild image feature has been successfully unlocked"
}
