{
  "MONSTER_DESCRIPTION": "सभी उपलब्ध राक्षसों की सूची प्रदर्शित करने के लिए यह कमांड का उपयोग करें, विस्तृत में जानकारी प्राप्त करने के लिए \"{{prefix}}monster <Name>\" कमांड का उपयोग करें",
  "MONSTER_NAME": "**नाम:**",
  "MONSTER_DEFEATED_one": "**हराया गया:** {{count}} बार",
  "MONSTER_DEFEATED_few": "**हराया गया:** {{count}} बार",
  "MONSTER_DEFEATED_other": "**हराया गया:** {{count}} बार",
  "MONSTER_DEFEATED_many": "**हराया गया:** {{count}} बार",
  "MONSTER_DEFEATED_zero": "**हराया गया:** {{count}} बार",
  "MONSTER_DEFEATED_two": "**हराया गया:** {{count}} बार",
  "MONSTER_ID": "**राक्षश की ID:**",
  "MONSTER_CAT": "**वर्ग:**",
  "MONSTER_TOP_DEFEATERS": "__**अव्वल खिलाड़ी**__",
  "MONSTER_TOP_DEFEATERS_LESS_MOVE": "__**कम बाजी मे अव्वल खिलाड़ी**__",
  "MONSTER_LAST_SPAWNED": "आखिरी बार प्रकट हुआ {{date}}",
  "CATALOGUE_EMBED_TITLE": "__Monster Catalogue__",

  "NO_RESULTS_FOUND": "{{author}} वह राक्षश ढूँढने मे असमर्थ",
  "MONSTER_CATEGORY": "गिल्डस",
  "NO_PLAYERS_FOUND": "कोई खिलाड़ी नहीं"
}
