{
    "WISHLIST_DESCRIPTION": "पसंदीदा-सूची दिखाता है",
    "CATEGORY": "WISHLIST",
    "USER_NOT_FOUND": "{{author}} वह उपयोगकर्ता ढूंढने में असमर्थ।",
    "WISHLIST_PRIVATE": "{{author}} इस उपयोगकर्ता की पसंदीदा-सूची निजी है।",
    "WISHLIST_EMPTY": "{{author}} इस उपयोगकर्ता की पसंदीदा-सूची खाली है।",
    "WISHLIST_EMBED_TITLE": "SOFI: WISHLIST ({{username}}) [{{length}}/{{slots}}]",
    "WISHLIST_EMBED_FOOTER": "पृष्ठ: {{page}}/{{totalPages}}",
    "COPY_CODES_BUTTON_LABEL": "कोड्स कॉपी करें",
    "COPY_CODES_MENU_LABEL": "सभी कोड्स",
    "COPY_CODES_MENU_DESCRIPTION": "सभी कोड्स को कॉपी करे",
    "BACK_MENU_LABEL": "वापस जाएं",
    "CARD_MENU_DESCRIPTION": "{{name}} के कोड्स कॉपी करें",
    "COPY_CODES_MENU_PLACEHOLDER": "विकल्प चुने",
    "CODES_COPIED": "← कॉपी किया गया",
    "ALL_CARD_CODES": "सभी कोड्स के भारी मात्रा में होने के कारण, संदेश को `.txt` रूप में बदला गया :",
    "WISHLIST_CODE_EMBED_TITLE": "SOFI: WISHLIST CODES",
    "WISHLIST_EMPTY_SELF": "{{author}} आपकी पसंदीदा-सूची खाली है।"
}
