{
    "BGS_SLASH_DESC": "Gib den Code des gesuchten \"Backgrounds\" ein",
    "BGSHOP_DESCRIPTION": "Zeigt den \"Background Shop\"",
    "BGS_CATEGORY": "Kosmetika",
    "EMBED_TITLE": "SOFI: BACKGROUND SHOP",
    "APPLY_BG": "\nVerwende den Befehl `{{prefix}}buy bg <Background-ID> <Amount>` um einen **Background** zu kaufen",
    "VIEW_BACKGROUNDS": "[Klicke hier um dir alle verfügbaren **Backgrounds** anzusehen](<https://sofi.gg/backgrounds>)",
    "SHOWING_PAGE": "Seite: {{page}}/{{pages}}",
    "NO_BG_FOUND": "{{author}} Es konnte kein **Background** mit dieser ID gefunden werden"
}
