{
  "DESCRIPTION": "- Wenn Sie den Befehl 'sc' verwenden, können Sie Ihre Kartensammlung anzeigen. Die Sammlungen können nach Namen, Gen, Wunschliste, angewandten Kosmetika, Kartenstatistiken, 3D-Verfügbarkeit sortiert und auch nach Wunschliste oder Generationsnummer oder Tag-Name gefiltert werden.\n-Typ sc t:ut, um unmarkierte Karten aus Ihrer Sammlung zu finden.",
  "SLASH_CMD_DESC": "Zeigen Sie Ihre Kartensammlung an",
  "SLASH_DESC": "Geben Sie den Benutzer ein, dessen Sammlung Sie anzeigen möchten",
  "SLASH_DESC2": "Geben Sie den Filter ein, den Sie auf die Sammlung anwenden möchten",
  "PLAYER_NOT_EXIST": "{{author}} | Dieser Spieler existiert nicht",
  "PLAYER_PRIVATE": "{{author}} | Die Sammlung dieses Benutzers ist privat!",
  "NO_RESULTS": "{{author}} | Keine Ergebnisse gefunden!",
  "NO_CARDS_FOUND": "{{author}} | Keine Karten gefunden, die Ihrer Suche entsprechen",
  "NOTHING_FOUND": "Nichts gefunden",
  "CHOOSE_SORTING": "Sortierung auswählen",
  "SORT_CHAR": "Figuren sortieren",
  "SORT_SERIES": "Nach Serie sortieren",
  "SORT_GEN": "Nach Generation sortieren",
  "SORT_WL": "Nach Wunschliste sortieren",
  "CHECK_COSMETICS": "Kosmetik prüfen",
  "3D_AVAIL": "3D-Verfügbarkeit",
  "SORT_ATK": "Nach Angriff sortieren",
  "SORT_DEF": "Nach Verteidigung sortieren",
  "SORT_SPEED": "Nach Geschwindigkeit sortieren",
  "SORT_HP": "Nach HP sortieren",
  "SORT_DUPE": "Nach Dupes sortieren",
  "SHOWING PAGE": "Seite anzeigen: {{page}}/{{pages}}",
  "ALL_UNTAG_SUCCESS": "Alle {{taglength}} Karten wurden erfolgreich unmarkiert",
  "ALL_TAG_SUCCESS": "{{author}} Alle {{taglength}} Karten wurden erfolgreich getaggt",
  "PLEASE_WAIT": "Bitte warten <a:ping:876612181725167687>",
  "NO_TAG_FOUND": "Wir schätzen den Kennzeichnungsaufwand, aber es wurden keine Tags gefunden"
}
