{
    "HELP_DESCRIPTION": "Verwende diesen Befehl ohne weitere Angaben, um eine Liste aller verfügbaren Befehle in Sofi anzuzeigen. Wenn du den Namen eines Befehls angibst, wird stattdessen eine Textbox mit einer Erklärung und der korrekten Nutzungsweise des Befehls aufgerufen",
    "HELP_SLASH_DESC": "Gib den Namen des Befehls ein, über den du mehr erfahren möchtest",
    "HELP_CATEGORY": "Einstellungen",
    "FILTER_EMBED_TITLE": "SOFI: COLLECTION FILTERS",
    "USE_FILTER_ORDER": "**__Sortiermöglichkeiten:__**\n\n<:pdot:979009081325019156> **Sortierung** = [`o`/`order`] | **`sc order wl>NUMMER o=d`**\n<:pdot:979009081325019156> **Absteigend** = [`d`] | **`sc order wl>NUMMER o=d`**\n<:pdot:979009081325019156> **Aufsteigend** = [`a`] | **`sc order wl>NUMMER o=a`**",
    "USE_FILTER_OPERATORS": "Achte darauf keine Leerzeichen vor & nach der Verwendung eines **Operators** zu benutzen!\n",
    "USE_FILTER_OPERATORS_2": "<:pdot:979009081325019156> **[`=`] [`:`] [`<`] [`>`] [`!=`] [`>=`] [`<=`]**",
    "USE_FILTER_OPERATORS_3": "<:pdot:979009081325019156> **`wl=NUMMER`** ← <:ticknobg:896960451215237250> \n<:pdot:979009081325019156> **`wl = NUMMER`**   ← <:crossnobg:896960454977527868>",
    "ALL_FILTER_CATEGORIES": "**__Verfügbare Kategorien:__** \n\n<:pdot:979009081325019156> **`Anime, Cartoon, Movie`** \n<:pdot:979009081325019156> **`Vtuber, Kpop, Jpop, Cpop`** \n<:pdot:979009081325019156> **`Art, Comic, Manga, Webtoon, Webseries`** \n<:pdot:979009081325019156> **`Games, Memes`**\n\n**__Event Abkürzungen:__**\n\n<:pdot:979009081325019156> **Halloween 2022** [`hal22`]\n<:pdot:979009081325019156> **Valentines 2023** [`val23`]\n<:pdot:979009081325019156> **Monochrome 2023** [`mon23`]\n<:pdot:979009081325019156> **Christmas 2023** [`xms23`]\n<:pdot:979009081325019156> **Spring 2024** [`spr24`]",
    "FILTER_NAME": "<:pdot:979009081325019156> **Name** = [`n`/`name`] | **`sc n=NAME`**\n<:pdot:979009081325019156> **Serie** = [`s`/`series`] | **`sc s=SERIE`**\n<:pdot:979009081325019156> **Datum** = [`d`/`date`] | **`sc d<DD/MM/YYYY`**\n<:pdot:979009081325019156> **Gen** = [`g`/`gen`] | **`sc g>GEN`**\n<:pdot:979009081325019156> **Wunschliste**= [`w`/`wl`/`wishlist`] | **`sc wl>=WUNSCHLISTE`**\n<:pdot:979009081325019156> **Seite** = [`p`] | **`sc p=NUMMER`**\n<:pdot:979009081325019156> **Element** = [`e`/`el`/`element`] | **`sc e=ELEMENT`**\n<:pdot:979009081325019156> **Tag** = [`t`/`tag`] | **`sc t=TAGNAME`**\n<:pdot:979009081325019156> **Angriff** = [`atk`/`attack`] | **`sc atk>NUMMER`**\n<:pdot:979009081325019156> **Verteidigung** = [`def`/`defense`] | **`sc def>NUMMER`**\n<:pdot:979009081325019156> **Geschwindigkeit** = [`spd`/`speed`] | **`sc spd>NUMMER`**\n<:pdot:979009081325019156> **Lebenspunkte** = [`hp`/`health`] | **`sc hp>NUMMER`**\n<:pdot:979009081325019156> **Code** = [`c`/`code`] | **`sc c=CODE`**\n<:pdot:979009081325019156> **Morphed** = [`m`/`morph`/`morphed`] | **`sc m=TRUE/FALSE`**\n<:pdot:979009081325019156> **3D** = [`3d`/`threed`] | **`sc 3d=TRUE/FALSE`**\n<:pdot:979009081325019156> **Glow** = [`glow`/`glowed`] | **`sc glow=TRUE/FALSE`**\n<:pdot:979009081325019156> **Frame** = [`f`/`frame`/`framed`] **`sc f=TRUE/FALSE`**\n<:pdot:979009081325019156> **Version** = [`v`/`ver`/`version`] | **`sc v=NUMMER`**\n<:pdot:979009081325019156> **Kategorie** = [`cat`/`category`] **`sc cat=KATEGORIE`**\n<:pdot:979009081325019156> **Level** = [`lvl`/`level`] | **`sc lvl>=NUMMER`**\n<:pdot:979009081325019156> **Event** = [`ev`/`event`] | **`sc ev:NAME/T`**",
    "BATTLE": "Kampf",
    "CARDS": "Karten",
    "GUILDS": "Gilden",
    "WISHLIST": "Wunschliste",
    "OWNER": "Besitzer",
    "SETTINGS": "Einstellungen",
    "TAGS": "Tags",
    "COSMETICS": "Kosmetika",
    "ALBUM": "Album",
    "SUPPORT_BUTTON_LABEL": "Support!",
    "DONATE_BUTTON_LABEL": "Spenden!",
    "TWITTER_BUTTON_LABEL": "Twitter!",
    "INVITE_BUTTON_LABEL": "Einladen!",
    "GUIDE_BUTTON_LABEL": "Anleitung!",
    "EMBED_TITLE": "SOFI: HELP MENU",
    "EMBED_FOOTER": "Angefragt von {{username}}",
    "COMMNAD_NOT_FOUND": "{{author}} | Es gibt keinen Befehl mit dem Namen `{{command}}`!\nMeintest du vielleicht `{{commandName}}`?",
    "USAGE_EMBED_TITLE": "SOFI: HELP ({{command}})",
    "ALIASES": "Aliase:",
    "COOLDOWN": "Abklingzeit:",
    "DESCRIPTION": "Beschreibung:",
    "USAGE": "Verwendung:",
    "NO_ALIASES": "Keine",
    "NOT_PROVIDED": "Nicht angegeben"
}
