{
  "MORPH_DESCRIPTION": "Cambia l'aspetto di una carta",
  "MORPH_CATEGORY": "Cosmetici",
  "CANNOT_MORPH": "{{author}} Il codice della carta che hai fornito non è valido o non è nella tua collezione",
  "NO_GIF_MORPHED": "{{author}} Non puoi usare morph sul'una carta `GIF`",
  "CONTINUE": "SOFI: MORPH",
  "MORPH_CONFIRMATION": "Sei sicuro di voler usare morph sulla tua carta **{{characterName}}** per **{{amount}}** {{currencyEmoji}} per rotolo?",
  "CANCELLED": "Il processo è stato annullato",
  "NOT_ENOUGH_SILVERS": "{{author}} Non hai abbastanza `{{currency}}` per questo processo",
  "BALANCE": "Saldo: **{{amount}}** {{currencyEmoji}}",
  "NAME": "Nome: **{{name}}**",
  "UNDO": "Morphs rolled: **{{count}}**",
  "FAILED": "{{author}} Qualcosa è andato storto, per favore riprova",
  "HISTORY": "\n**__Storia__**\n```{{history}}```",
  "STOLE_MORPH": "Qualcosa è andato storto, per favore rolla un'altra morph",
  "NO_ITEM": "{{author}} Non hai abbastanza `{{item}}`",
  "NO_CARD": "{{author}} La carta non è più nella tua collezione",
  "MORPH_CONFRIM": "{{author}} Hai applicato con successo il morph **{{morphName}}** alla tua carta",
  "REROLL": "\nNon puoi annullare più morphs",
  "UNDO_SUCCESSFUL": "\nRestaurato il morph precedente per **{{amount}}** {{emoji}}",
  "CORRECT_USAGE": "{{author}} Uso corretto: `{{prefix}}m <CodiceDellaCarta> <MorphItem>`",
  "ROLL_MORPH": "il morph sarà perderà dopo 2 minuti",
  "NONE": "Nessuno",
  "MNC_CARDS_CANNOT_MORPH": "{{author}} Le carte 3D Monochrome 2023 non possono essere morphed",
  "MNC_EMBED_TITLE": "**[SOFI: MORPH](https://guide.sofi.gg)**",
  "EMBED_TITLE": "**[SOFI: MORPH](https://guide.sofi.gg)**",
  "CANNOT_APPLY_MNC": "{{author}} Non puoi applicare il morph {{article}} `{{eventType}}` sulle carte `{{eventCardType}}` o `3D`",
  "MNC_REROLL_COST": "Ogni rotolo costerà 1 \"{{currencyName}}\"",
  "NO_SPECIAL_REROLLED": "Nessuna morph speciale rolled"
}