{
    "SWAP_DESCRIPTION": "\"Swaps\" i cosmetici tra due carte",
    "SWAP_CATEGORY": "Cosmetici",
    "MENU_FRAME_LABEL": "Cornice",
    "MENU_FRAME_DESC": "\"Swaps\" i \"Frames\" di due carte",
    "MENU_TEXT_LABEL": "Visibilità del testo",
    "MENU_TEXT_DESC": "\"Swaps\" la visibilità del testo di due carte",
    "MENU_COLOR_LABEL": "Colore del carattere",
    "MENU_COLOR_DESC": "\"Swaps\" il colore del carattere di due carte",
    "MENU_MORPH_LABEL": "Morph",
    "MENU_MORPH_DESC": "\"Swaps\" i \"Morphs\" di due carte",
    "MENU_GLOW_LABEL": "Bagliore",
    "MENU_GLOW_DESC": "Scambio di bagliore / superluce di due carte",
    "MENU_BG_LABEL": "Sfondi",
    "MENU_BG_DESC": "Scambia sfondi di carte 3D",
    "PROVIDE_CODES": "{{author}} devi fornire i codici della carta: sswap <code1> <code2>",
    "NO_GIF": "{{author}} i cosmetici gif non possono essere scambiati",
    "NO_COSMETICS": "{{author}} Le tue carte non hanno cosmetici da scambiare",
    "MENU_FEATURES_PLACEHOLDER": "Scegli le funzionalità da scambiare",
    "EMBED_TITLE": "SOFI: SERVIZIO DI SCAMBIO",
    "CHOOSE_FROM_OPTIONS": "Scegli tra le opzioni disponibili per scambiare..",
    "EMBED_FOOTER": "Il processo consumerà alcuni oggetti di scambio",
    "SWAPS_CHOSEN": "Scambi scelti:",
    "MISSING_SWAP_TOKEN": "{{author}} manca il token di scambio..",
    "SUS_THING": "{{authorId}} ha fatto una cosa sospetta con lo swap....",
    "DOES_NOT_WORK": "Vedo cosa stai cercando qui.. ma non funziona",
    "SWAP_SUCCESSFULL": "Lo scambio è stato effettuato con successo"
}
