{
  "WISHLISTUPGRADE_DESCRIPTION": "Aumenta la capacità della tua wishlist",
  "CATEGORY": "Wishlist",
  "ALREADY_MAXED": "{{author}} Non puoi più aggiornare la tua wishlist",
  "EMBED_DESCRIPTION": "Sei sicuro di voler acquistare **{{count}}** slot extra per **{{amount}}** `{{currency}}`?",
  "EMBED_PAY_FIELD_NAME": "Pagherai:",
  "EMBED_PAY_FIELD_VALUE": "```{{amount}} {{currency}}```",
  "EMBED_GET_FIELD_NAME": "Ricevi:",
  "EMBED_GET_FIELD_VALUE": "```{{count}} slot aggiuntivi per wishlist```",
  "EMBED_MAXED_DESCRIPTION": "Sei sicuro di voler aumentare la tua wishlist al massimo per **{{amount}}** `{{currency}}`?",
  "EMBED_MAXED_FIELD_VALUE": "```Slot massimi di wishlist (50 Slots)```",
  "CANCELLED": "Il processo è stato annullato",
  "PAY_ERROR": "{{author}} Non hai abbastanza `{{currency}}` per questo processo",
  "EMBED_TITLE": "SOFI: WISHLISTUPGRADE",
  "WISHLIST_UPGRADE_SUCCESSFUL": "{{author}} Ha aggiornato con successo il tuo wishlist"
}
