{
    "PULL_DESCRIPTION": "يستخرج عناصر مختلفة مثل السواب، والأساور، وقطع البطاقات المتحركة",
    "PULL_AMT": "{{user}} يرجى تحديد عدد مرات الاستحواذ بمقدار 1 أو 10",
    "INFO_1": "فرصة الحصول على قطعة تبلغ 12٪",
    "INFO_2": "فرص الحصول على الأساور والسوابات منخفضة",
    "INFO_3": "يحتاج كل شخصية متحركة إلى 8 قطع",
    "PULLS": "SOFI: PULLS",
    "PULL_COUNT": "عدد السحوبات: {{count}}",
    "MISSING_CURR": "{{user}} ليس لديه {{amount}} {{currName}}",
    "AMOUNT": "المبلغ: {{amount}}",
    "PULL_COUNT_WIST": "عدد السحوبات: {{pullcount}} | يمكنك شراء WIST من متجر المقاصة"
}
