{
    "DESCRIPTION": "Отправляет запрос на обмен другому игроку. С помощью этой функции вы можете одновременно обменивать несколько карточек и \"Items\"",
    "MENTION_USER": "{{author}} Упомяните пользователя, с которым хотите сделать обмен, или используйте его идентификатор",
    "IN_TRADE": "{{user}} Вы уже отправили запрос на обмен кому-то! Сначала отмените предыдущий запрос, прежде чем начинать новый",
    "BOT_TRADE": "{{author}} `Bot`не можете торговать с вами",
    "SELF_TRADE": "{{author}} Вы не можете торговать с самим собой",
    "NOT_REGISTERED": "{{user}} еще не зарегистрирован!",
    "AUTHOR_IS_BLED": "{{author}} Вы в черном списке",
    "MEMBER_IS_BLED": "{{user}} в черном списке",
    "AUTHOR_IS_QUED": "{{author}} Вы находитесь в карантине",
    "MEMBER_IS_QUED": "{{user}} находится в карантине",
    "BUY_TP_1": "У {{user}} нет активного `Trade Pass`",
    "BUY_TP_2": "Вы можете обменять **__1x__** `Bump` на 4-часовой `Trade Pass` или накопить **__20x__** `Bumps`, чтобы купить на 30 дней `Trade Pass`",
    "FINISH_TRADE_WARN": "{{author}} Завершите команду {{commandName}}, прежде чем продолжить.",
    "SENT_TRADE": "{{author}} отправил вам запрос на обмен",
    "ENTER_NOTE": "Введите заметку",
    "EXAMPLE:": "Добавьте контекст для сделки, которая кажется подозрительной",
    "MODAL_TITLE": "Мульти трейд:",
    "NOTED_ADDED": "Заметка добавлена: {{response}}",
    "TRADE_CANCELLED": "Обмен был отменен",
    "MT_ENDS": "Мульти трейд заканчивается {{timer}}",
    "MT_INFO_1": "🤝 Префиксы: `Background [&]` `Glow [#]` `Fragments[-]` `Frames [$]` `Tag [%]`",
    "MT_INFO_2": "🔮 `Crystal` аббревиатура🔥 `[fi-c]` 🌲 `[wo-c]` и т.д.",
    "MT_INFO_3": "🗒️ Добавляйте заметки к вашей сделке, чтобы добавить контекст для наших логов",
    "MT_INFO_4": "📛 Сообщайте о игроках, запрашивающих оплату в криптовалюте, так как это является запрещенным действием и может привести к блокировке аккаунта!",
    "MT_COMPLETE": "Мульти трейд: (Завершено)",
    "MISSING_ITEMS": "{{user}} Cледующие предметы отсутствуют в вашем `Inventory` и не могут быть добавлены:\n`{{items}}`",
    "CARD_LOCKED": "{{user}} Cледующие карты заблокированы или в настоящее время используются в колоде и не могут быть добавлены:\n{{codes}}"
}
